[
	{
		"title": "Sound",
		"options": [
			{
				"title": "Inputs",
				"description": "Every sound event has inputs. Some examples are a microphone, an instrument such as a keyboard or electric guitar, or a phone. For most events, the number of inputs is the number of microphones. We do not count inputs from our own laptop for playing music.",
				"choices": [
					{
						"title": "Small",
						"value": "I1",
						"price": 50,
						"detailPrompt": "Please describe your microphone and laptop/phone input requirements.",
						"description": "Music and up to 2 inputs. Suitable for speaking events, small performances, or background music."
					},
					{
						"title": "Medium",
						"value": "I2",
						"price": 75,
						"detailPrompt": "Please describe your microphone and other input requirements, including any instruments/vocalists that need to be mic'ed, any DIs required, laptop input, etc.",
						"description": "Music and up to 8 inputs. Suitable for panel discussions or small performances."
					},
					{
						"title": "Large",
						"value": "I3",
						"price": 150,
						"detailPrompt": "Please describe your microphone and other input requirements, including any instruments/vocalists that need to be mic'ed, any DIs required, etc. If your event is a stage show with multiple acts, you will be asked for a set list via email and you only need to provide a general description here.",
						"description": "Unlimited inputs. Suitable for large stage shows, concerts, bands, or other large events."
					}
				]
			},
			{
				"title": "Speakers",
				"description": "If your event needs more than two main speakers, such as for surround sound or a large concert, contact us.",
				"choices": [
					{
						"title": "House System",
						"value": "O1",
						"price": 0,
						"description": "We will use the speakers that are permanently installed in the venue."
					},
					{
						"title": "Small",
						"value": "O2",
						"price": 80,
						"description": "Two small speakers. Suitable for speaking events, casual background music, or small event spaces."
					},
					{
						"title": "Large",
						"value": "O3",
						"price": 120,
						"description": "Two larger speakers. Suitable for stage shows, dances, or larger event spaces."
					}
				]
			},
			{
				"title": "Subwoofers",
				"isBoolean": true,
				"choices": [
					{
						"title": "Subwoofers",
						"value": "SB",
						"price": 50,
						"description": "Subwoofers add bass to your event's sound. Recommended for bands, stage shows, or dances. Suitable for most events involving music."
					}
				],
				"defaultChoice": "No"
			},
			{
				"title": "Stage Monitors",
				"isBoolean": true,
				"choices": [
					{
						"title": "Stage Monitors",
						"value": "SM",
						"price": 30,
						"detailPrompt": "Please describe your monitor requirements.",
						"description": "Monitors for on-stage performers. Recommended for stage shows and bands."
					}
				],
				"defaultChoice": "No"
			},
			{
				"title": "Area Fills",
				"isBoolean": true,
				"choices": [
					{
						"title": "Area Fills",
						"value": "AF",
						"price": 20,
						"description": "Additional speakers to fill a large or oddly-shaped venue."
					}
				],
				"defaultChoice": "No"
			}
		],
		"addons": [
			{
				"title": "Wireless Microphone",
				"description": "Wired microphones are included but there is a fee per wireless microphone.",
				"price": 10
			}
		]
	},
	{
		"title": "Lighting",
		"options": [
			{
				"title": "Stage lighting",
				"choices": [
					{
						"title": "None",
						"value": null,
						"price": 0
					},
					{
						"title": "Basic",
						"value": "W1",
						"price": 99999,
						"detailPrompt": "Please describe your needs.",
						"description": "Basic static lighting for your stage or performance area. No changing colors, moving lights, different scenes, etc. Maximum of 8 fixtures.",
						"imageUrl": "assets/images/stage_basic.jpg"
					},
					{
						"title": "Advanced",
						"value": "W2",
						"price": 99999,
						"detailPrompt": "Please describe your needs.",
						"description": "Anything more than Basic.",
						"imageUrl": "assets/images/stage_advanced.jpg"
					}
				],
				"defaultChoice": "None"
			},
			{
				"title": "Area lighting",
				"description": "Lorem ipsum dolor sit amet, consectetur adipiscing elit. Nunc eu sem elit. Mauris varius quis nulla ut condimentum.",
				"choices": [
					{
						"title": "None",
						"value": null,
						"price": 0
					},
					{
						"title": "Basic",
						"value": "A1",
						"price": 50,
						"detailPrompt": "Please describe your needs.",
						"description": "Basic area lighting that can be dimmed. No changing colors, moving lights, different scenes, etc.",
						"imageUrl": "assets/images/area_basic.jpg"
					},
					{
						"title": "Advanced",
						"value": "A2",
						"price": 75,
						"detailPrompt": "Please describe your needs.",
						"description": "Anything more than Basic.",
						"imageUrl": "assets/images/area_advanced.jpg"
					}
				],
				"defaultChoice": "None"
			},
			{
				"title": "Uplighting",
				"isBoolean": true,
				"choices": [
					{
						"title": "Uplighting",
						"value": "UP",
						"price": 50,
						"description": "Prettify the room.",
						"imageUrl": "assets/images/uplighting.jpg"
					}
				],
				"defaultChoice": "No"
			},
			{
				"title": "Haze",
				"description": "We own one fog machine and can rent more to suit your needs. Use of haze requires a fire watch which you must arrange and pay for.",
				"isBoolean": true,
				"choices": [
					{
						"title": "Haze",
						"value": "HZ",
						"price": 20,
						"imageUrl": "assets/images/haze.jpg"
					}
				],
				"defaultChoice": "No"
			},
			{
				"title": "Rigging",
				"description": "Lorem ipsum dolor sit amet, consectetur adipiscing elit. Nunc eu sem elit. Mauris varius quis nulla ut condimentum.",
				"choices": [
					{
						"title": "None",
						"value": null,
						"price": 0
					},
					{
						"title": "Basic",
						"value": "R1",
						"price": 60,
						"imageUrl": "assets/images/rigging_basic.jpg"
					},
					{
						"title": "Advanced",
						"value": "R2",
						"price": 120,
						"imageUrl": "assets/images/rigging_advanced.jpg"
					}
				],
				"defaultChoice": "None"
			},
			{
				"title": "Flown projector",
				"isBoolean": true,
				"choices": [
					{
						"title": "Truss-mounted projector",
						"value": "RP",
						"price": 20,
						"imageUrl": "assets/images/flown_projector.jpg"
					}
				],
				"defaultChoice": "No"
			}
		],
		"addons": [
			{
				"title": "Special spot / photo booth light",
				"description": "For all your inconveniently-located lighting needs",
				"price": 10
			}
		]
	},
	{
		"title": "Other",
		"options": [
			{
				"title": "Power Distribution",
				"isBoolean": true,
				"choices": [
					{
						"title": "Power Distribution",
						"value": "PD",
						"price": 40,
						"description": "Power your pizza warmers or something."
					}
				],
				"defaultChoice": "No"
			}
		]
	}
]
